{
  "stages": { "description": "De 3 à 15 jours au départ de Marseille ou PACA. Stage adapté au niveau du groupe (FFVoile niveaux 1 à 4), pour 3 à 6 personnes.", "photo": "" },
  "croisieres": { "description": "EVJF/EVG, carto-trésor, observation de la faune marine, voile multi-disciplines, mixité choisie, traversées solidaires.", "photo": "" },
  "stages_pre": { "description": "Rejoignez d'autres élèves sur un stage déjà planifié. Voile-ornitho, voile-cétacés, stage du 8 mai…", "photo": "" },
  "cours_prive": { "description": "Cours sur mesure, à votre rythme, sur vos objectifs.", "photo": "" }
}
